allgreen/__init__.py
allgreen/config.py
allgreen/core.py
allgreen/rate_limiting.py
allgreen/integrations/__init__.py
allgreen/integrations/django_integration.py
allgreen/integrations/fastapi_integration.py
allgreen/integrations/flask_integration.py
allgreen/templates/healthcheck.html
allgreen/templates/allgreen/healthcheck.html
allgreen-0.11.0.dist-info/licenses/LICENSE
allgreen-0.11.0.dist-info/METADATA
allgreen-0.11.0.dist-info/WHEEL
allgreen-0.11.0.dist-info/top_level.txt
allgreen-0.11.0.dist-info/RECORD
