Metadata-Version: 2.4
Name: allgreen
Version: 0.11.0
Summary: Simple, beautiful health checks for Python applications
Author-email: Navin Pai <lifeofnavin@gmail.com>
License: MIT
Project-URL: Homepage, https://github.com/navinpai/allgreen
Project-URL: Repository, https://github.com/navinpai/allgreen
Project-URL: Issues, https://github.com/navinpai/allgreen/issues
Classifier: Development Status :: 3 - Alpha
Classifier: Intended Audience :: Developers
Classifier: License :: OSI Approved :: MIT License
Classifier: Programming Language :: Python :: 3
Classifier: Programming Language :: Python :: 3.10
Classifier: Programming Language :: Python :: 3.11
Classifier: Programming Language :: Python :: 3.12
Requires-Python: >=3.10
License-File: LICENSE
Provides-Extra: flask
Requires-Dist: flask>=2.0.0; extra == "flask"
Requires-Dist: jinja2>=3.0.0; extra == "flask"
Provides-Extra: django
Requires-Dist: django>=3.2; extra == "django"
Provides-Extra: fastapi
Requires-Dist: fastapi>=0.68.0; extra == "fastapi"
Requires-Dist: uvicorn>=0.15.0; extra == "fastapi"
Requires-Dist: jinja2>=3.0.0; extra == "fastapi"
Provides-Extra: dev
Requires-Dist: pytest>=7.0.0; extra == "dev"
Requires-Dist: pytest-cov; extra == "dev"
Requires-Dist: ruff; extra == "dev"
Requires-Dist: flask>=2.0.0; extra == "dev"
Requires-Dist: jinja2>=3.0.0; extra == "dev"
Dynamic: license-file
